arraypartition/__init__.py
arraypartition/partition.py
arraypartition/tests/data/example1.0.nc
arraypartition/tests/test_array.py
arraypartition/tests/test_consistency.py
arraypartition-1.2.0.dist-info/METADATA
arraypartition-1.2.0.dist-info/WHEEL
arraypartition-1.2.0.dist-info/licenses/LICENSE
arraypartition-1.2.0.dist-info/RECORD
