Metadata-Version: 2.4
Name: arraypartition
Version: 1.2.0
Summary: Container module for ArrayLike Partition class behaviour
License: BSD 3
License-File: LICENSE
Author: Daniel Westwood
Author-email: daniel.westwood@stfc.ac.uk
Requires-Python: >=3.11,<4.0
Classifier: License :: Other/Proprietary License
Classifier: Programming Language :: Python :: 3
Classifier: Programming Language :: Python :: 3.11
Classifier: Programming Language :: Python :: 3.12
Classifier: Programming Language :: Python :: 3.13
Classifier: Programming Language :: Python :: 3.14
Requires-Dist: dask (>=2025.3.0)
Requires-Dist: netcdf4 (>=1.7.2)
Requires-Dist: numpy (>=2.0.0)
